{
  "directed": false,
  "multigraph": false,
  "graph": {},
  "nodes": [
    {
      "imdb_title_id": "tt0983946",
      "title": "Fantasy Island",
      "original_title": "Fantasy Island",
      "year": 2020,
      "date_published": "2020-02-13",
      "genre": ["Action", "Adventure", "Fantasy"],
      "duration": 109,
      "country": ["USA"],
      "language": ["English"],
      "director": ["Jeff Wadlow"],
      "writer": ["Jillian Jacobs", "Christopher Roach"],
      "production_company": "Columbia Pictures",
      "actors": [
        "Michael Pe帽a",
        "Maggie Q",
        "Lucy Hale",
        "Austin Stowell",
        "Jimmy O. Yang",
        "Portia Doubleday",
        "Ryan Hansen",
        "Michael Rooker",
        "Parisa Fitz-Henley",
        "Mike Vogel",
        "Kim Coates",
        "Robbie Jones",
        "Jeriya Benn",
        "Charlotte McKinney",
        "Josh McConville"
      ],
      "description": "When the owner and operator of a luxurious island invites a collection of guests to live out their most elaborate fantasies in relative seclusion, chaos quickly descends.",
      "avg_vote": 4.9,
      "votes": 26823,
      "budget": 7000000,
      "usa_gross_income": 26441782,
      "worlwide_gross_income": 47315959,
      "metascore": 22,
      "reviews_from_users": 635,
      "reviews_from_critics": 154,
      "id": 1
    },
    {
      "imdb_title_id": "tt10059518",
      "title": "Il giorno sbagliato",
      "original_title": "Unhinged",
      "year": 2020,
      "date_published": "2020-09-24",
      "genre": ["Action", "Thriller"],
      "duration": 90,
      "country": ["USA"],
      "language": ["English"],
      "director": ["Derrick Borte"],
      "writer": ["Carl Ellsworth"],
      "production_company": "Burek Films",
      "actors": [
        "Russell Crowe",
        "Caren Pistorius",
        "Jimmi Simpson",
        "Gabriel Bateman",
        "Anne Leighton",
        "Austin P. McKenzie",
        "Lucy Faust",
        "Michael Papajohn",
        "Brett Smrz",
        "Juliene Joyner",
        "Stephen Louis Grush",
        "Sylvia Grace Crim",
        "Gregory Hobson",
        "Devyn A. Tyler",
        "Hick Cheramie"
      ],
      "description": "After a confrontation with an unstable man at an intersection, a woman becomes the target of his rage.",
      "avg_vote": 6.2,
      "votes": 4720,
      "budget": 33000000,
      "usa_gross_income": 9025406,
      "worlwide_gross_income": 21025406,
      "metascore": 40,
      "reviews_from_users": 159,
      "reviews_from_critics": 119,
      "id": 2
    },
    {
      "imdb_title_id": "tt1051906",
      "title": "L'uomo invisibile",
      "original_title": "The Invisible Man",
      "year": 2020,
      "date_published": "2020-03-27",
      "genre": ["Horror", "Mystery", "Sci-Fi"],
      "duration": 124,
      "country": ["Canada", "Australia", "USA"],
      "language": ["English"],
      "director": ["Leigh Whannell"],
      "writer": ["Leigh Whannell", "Leigh Whannell"],
      "production_company": "Universal Pictures",
      "actors": [
        "Elisabeth Moss",
        "Oliver Jackson-Cohen",
        "Harriet Dyer",
        "Aldis Hodge",
        "Storm Reid",
        "Michael Dorman",
        "Benedict Hardie",
        "Renee Lim",
        "Brian Meegan",
        "Nick Kici",
        "Vivienne Greer",
        "Nicholas Hope",
        "Cleave Williams",
        "Cardwell Lynch",
        "Sam Smith"
      ],
      "description": "When Cecilia's abusive ex takes his own life and leaves her his fortune, she suspects his death was a hoax. As a series of coincidences turn lethal, Cecilia works to prove that she is being hunted by someone nobody can see.",
      "avg_vote": 7.1,
      "votes": 129805,
      "budget": 7000000,
      "usa_gross_income": 64914050,
      "worlwide_gross_income": 130620744,
      "metascore": 72,
      "reviews_from_users": 1458,
      "reviews_from_critics": 403,
      "id": 7
    },
    {
      "imdb_title_id": "tt1502397",
      "title": "Bad Boys for Life",
      "original_title": "Bad Boys for Life",
      "year": 2020,
      "date_published": "2020-02-20",
      "genre": ["Action", "Comedy", "Crime"],
      "duration": 124,
      "country": ["USA", "Mexico"],
      "language": ["English", "Spanish"],
      "director": ["Adil El Arbi", "Bilall Fallah"],
      "writer": ["Peter Craig", "Joe Carnahan"],
      "production_company": "Columbia Pictures",
      "actors": [
        "Will Smith",
        "Martin Lawrence",
        "Vanessa Hudgens",
        "Alexander Ludwig",
        "Charles Melton",
        "Paola Nu帽ez",
        "Kate del Castillo",
        "Nicky Jam",
        "Joe Pantoliano",
        "Jacob Scipio",
        "Theresa Randle",
        "DJ Khaled",
        "Happy Anderson",
        "Bianca Bethune",
        "Dennis Greene"
      ],
      "description": "Miami detectives Mike Lowrey and Marcus Burnett must face off against a mother-and-son pair of drug lords who wreak vengeful havoc on their city.",
      "avg_vote": 6.6,
      "votes": 111557,
      "budget": 90000000,
      "usa_gross_income": 204417855,
      "worlwide_gross_income": 424617855,
      "metascore": 59,
      "reviews_from_users": 1072,
      "reviews_from_critics": 238,
      "id": 27
    },
    {
      "imdb_title_id": "tt1634106",
      "title": "Bloodshot",
      "original_title": "Bloodshot",
      "year": 2020,
      "date_published": "2020-03-27",
      "genre": ["Action", "Drama", "Sci-Fi"],
      "duration": 109,
      "country": ["USA"],
      "language": ["English", "Persian"],
      "director": ["Dave Wilson"],
      "writer": ["Jeff Wadlow", "Eric Heisserer"],
      "production_company": "Columbia Pictures",
      "actors": [
        "Vin Diesel",
        "Eiza Gonz谩lez",
        "Sam Heughan",
        "Toby Kebbell",
        "Talulah Riley",
        "Lamorne Morris",
        "Guy Pearce",
        "J贸hannes Haukur J贸hannesson",
        "Alex Hernandez",
        "Siddharth Dhananjay",
        "Tamer Burjaq",
        "Clyde Berning",
        "David Dukas",
        "Charlie Bouguenon",
        "Tyrel Meyer"
      ],
      "description": "Ray Garrison, a slain soldier, is re-animated with superpowers.",
      "avg_vote": 5.7,
      "votes": 49627,
      "budget": 45000000,
      "usa_gross_income": 10021787,
      "worlwide_gross_income": 30855391,
      "metascore": 44,
      "reviews_from_users": 672,
      "reviews_from_critics": 188,
      "id": 28
    },
    {
      "imdb_title_id": "tt2420124",
      "title": "Wendy",
      "original_title": "Wendy",
      "year": 2020,
      "date_published": "2020-04-17",
      "genre": ["Drama", "Fantasy"],
      "duration": 111,
      "country": ["USA"],
      "language": ["English"],
      "director": ["Benh Zeitlin"],
      "writer": ["Benh Zeitlin", "Eliza Zeitlin"],
      "production_company": "Fox Searchlight Pictures",
      "actors": [
        "Devin France",
        "Yashua Mack",
        "Gage Naquin",
        "Gavin Naquin",
        "Ahmad Cage",
        "Krzysztof Meyn",
        "Romyri Ross",
        "Lowell Landes",
        "Kevin Pugh",
        "Shay Walker",
        "Stephanie Lynn Wilson",
        "Pam Harper",
        "Cleopatra King Welch",
        "Allison Campbell",
        "Catherine Ott"
      ],
      "description": "Lost on a mysterious island where aging and time have come unglued, Wendy must fight to save her family, her freedom, and the joyous spirit of youth from the deadly peril of growing up.",
      "avg_vote": 5.7,
      "votes": 1405,
      "budget": 6000000,
      "usa_gross_income": 143518,
      "worlwide_gross_income": 144564,
      "metascore": 54,
      "reviews_from_users": 41,
      "reviews_from_critics": 52,
      "id": 30
    },
    {
      "imdb_title_id": "tt3547306",
      "title": "Cut Throat City",
      "original_title": "Cut Throat City",
      "year": 2020,
      "date_published": "2020-08-21",
      "genre": ["Action", "Crime", "Drama"],
      "duration": 123,
      "country": ["USA"],
      "language": ["English"],
      "director": ["RZA"],
      "writer": ["P.G. Cuschieri"],
      "production_company": "Rumble Riot Pictures",
      "actors": [
        "Eiza Gonz谩lez",
        "Ethan Hawke",
        "Kat Graham",
        "Wesley Snipes",
        "Keean Johnson",
        "Isaiah Washington",
        "Terrence Howard",
        "Joel David Moore",
        "Shameik Moore",
        "Denzel Whitaker",
        "Andrene Ward-Hammond",
        "Sam Daly",
        "T.I.",
        "Rob Morgan",
        "Demetrius Shipp Jr."
      ],
      "description": "Set after Hurricane Katrina, four boyhood friends out of options reluctantly accept an offer to pull off a dangerous heist in the heart of New Orleans.",
      "avg_vote": 4.3,
      "votes": 141,
      "budget": 8000000,
      "usa_gross_income": 507436,
      "worlwide_gross_income": 507974,
      "metascore": 67,
      "reviews_from_users": 6,
      "reviews_from_critics": 22,
      "id": 35
    },
    {
      "imdb_title_id": "tt3612126",
      "title": "The Grudge",
      "original_title": "The Grudge",
      "year": 2020,
      "date_published": "2020-03-05",
      "genre": ["Horror", "Mystery"],
      "duration": 94,
      "country": ["USA", "Canada"],
      "language": ["English"],
      "director": ["Nicolas Pesce"],
      "writer": ["Nicolas Pesce", "Nicolas Pesce"],
      "production_company": "Screen Gems",
      "actors": [
        "Tara Westwood",
        "Junko Bailey",
        "David Lawrence Brown",
        "Zoe Fish",
        "Andrea Riseborough",
        "John J. Hansen",
        "Demi谩n Bichir",
        "Joel Marsh Garland",
        "Bradley Sawatzky",
        "Duke",
        "Bruno The Dog",
        "Lin Shaye",
        "John Cho",
        "Betty Gilpin",
        "Stephanie Sy"
      ],
      "description": "A house is cursed by a vengeful ghost that dooms those who enter it with a violent death.",
      "avg_vote": 4.2,
      "votes": 17156,
      "budget": 10000000,
      "usa_gross_income": 21221803,
      "worlwide_gross_income": 49511319,
      "metascore": 41,
      "reviews_from_users": 525,
      "reviews_from_critics": 178,
      "id": 36
    },
    {
      "imdb_title_id": "tt3794354",
      "title": "Sonic - Il film",
      "original_title": "Sonic the Hedgehog",
      "year": 2020,
      "date_published": "2020-02-13",
      "genre": ["Action", "Adventure", "Comedy"],
      "duration": 99,
      "country": ["USA", "Japan", "Canada"],
      "language": ["English", "French"],
      "director": ["Jeff Fowler"],
      "writer": ["Pat Casey", "Josh Miller"],
      "production_company": "Paramount Pictures",
      "actors": [
        "Ben Schwartz",
        "James Marsden",
        "Jim Carrey",
        "Tika Sumpter",
        "Natasha Rothwell",
        "Adam Pally",
        "Lee Majdoub",
        "Neal McDonough",
        "Tom Butler",
        "Frank C. Turner",
        "Melody Nosipho Niemann",
        "Shannon Chan-Kent",
        "Brad Kelly",
        "Elfina Luk",
        "Garry Chalk"
      ],
      "description": "After discovering a small, blue, fast hedgehog, a small-town police officer must help him defeat an evil genius who wants to do experiments on him.",
      "avg_vote": 6.5,
      "votes": 74639,
      "budget": 85000000,
      "usa_gross_income": 146066470,
      "worlwide_gross_income": 306766470,
      "metascore": 47,
      "reviews_from_users": 1018,
      "reviews_from_critics": 250,
      "id": 37
    },
    {
      "imdb_title_id": "tt4682266",
      "title": "New Mutants",
      "original_title": "The New Mutants",
      "year": 2020,
      "date_published": "2020-09-02",
      "genre": ["Action", "Horror", "Sci-Fi"],
      "duration": 94,
      "country": ["USA", "Canada"],
      "language": ["English"],
      "director": ["Josh Boone"],
      "writer": ["Josh Boone", "Knate Lee"],
      "production_company": "20th Century Studios",
      "actors": [
        "Maisie Williams",
        "Anya Taylor-Joy",
        "Charlie Heaton",
        "Alice Braga",
        "Blu Hunt",
        "Henry Zaga",
        "Adam Beach",
        "Thomas Kee",
        "Colbi Gannett",
        "Happy Anderson",
        "Dustin Ceithamer",
        "Jacinto Vega SpiritWolf",
        "Chuck",
        "Marilyn Manson"
      ],
      "description": "Five young mutants, just discovering their abilities while held in a secret facility against their will, fight to escape their past sins and save themselves.",
      "avg_vote": 5.6,
      "votes": 4621,
      "budget": 67000000,
      "usa_gross_income": 7487310,
      "worlwide_gross_income": 10387310,
      "metascore": 41,
      "reviews_from_users": 173,
      "reviews_from_critics": 54,
      "id": 40
    },
    {
      "imdb_title_id": "tt5259822",
      "title": "Tesla",
      "original_title": "Tesla",
      "year": 2020,
      "date_published": "2020-08-21",
      "genre": ["Biography", "Drama"],
      "duration": 102,
      "country": ["USA"],
      "language": ["English"],
      "director": ["Michael Almereyda"],
      "writer": ["Michael Almereyda"],
      "production_company": "Passage Pictures (II)",
      "actors": [
        "Ethan Hawke",
        "Eve Hewson",
        "Eli A. Smith",
        "Josh Hamilton",
        "Lucy Walters",
        "Luna Jokic",
        "Kyle MacLachlan",
        "Dan Bittner",
        "David Kallaway",
        "Karl Geary",
        "Ebon Moss-Bachrach",
        "Nicholas Wuehrmann",
        "Haley Elise Pehrson",
        "Tony Hutaj",
        "Corban Elwick-Schermitz"
      ],
      "description": "A freewheeling take on visionary inventor Nikola Tesla, his interactions with Thomas Edison and J.P. Morgan's daughter Anne, and his breakthroughs in transmitting electrical power and light.",
      "avg_vote": 5.1,
      "votes": 2277,
      "budget": 5000000,
      "usa_gross_income": 76263,
      "worlwide_gross_income": 79603,
      "metascore": 68,
      "reviews_from_users": 93,
      "reviews_from_critics": 74,
      "id": 43
    },
    {
      "imdb_title_id": "tt5774060",
      "title": "Underwater",
      "original_title": "Underwater",
      "year": 2020,
      "date_published": "2020-01-30",
      "genre": ["Action", "Horror", "Sci-Fi"],
      "duration": 95,
      "country": ["USA"],
      "language": ["English"],
      "director": ["William Eubank"],
      "writer": ["Brian Duffield", "Adam Cozad"],
      "production_company": "20th Century Fox Film Corporation",
      "actors": [
        "Kristen Stewart",
        "Vincent Cassel",
        "Mamoudou Athie",
        "T.J. Miller",
        "John Gallagher Jr.",
        "Jessica Henwick",
        "Gunner Wright",
        "Fiona Rene",
        "Amanda Troop"
      ],
      "description": "A crew of oceanic researchers working for a deep sea drilling company try to get to safety after a mysterious earthquake devastates their deepwater research and drilling facility located at the bottom of the Mariana Trench.",
      "avg_vote": 5.8,
      "votes": 48505,
      "budget": 80000000,
      "usa_gross_income": 17291078,
      "worlwide_gross_income": 40882928,
      "metascore": 48,
      "reviews_from_users": 795,
      "reviews_from_critics": 233,
      "id": 48
    },
    {
      "imdb_title_id": "tt6673612",
      "title": "Dolittle",
      "original_title": "Dolittle",
      "year": 2020,
      "date_published": "2020-01-30",
      "genre": ["Adventure", "Comedy", "Family"],
      "duration": 101,
      "country": ["USA", "China", "UK", "Japan"],
      "language": ["English", "French"],
      "director": ["Stephen Gaghan"],
      "writer": ["Stephen Gaghan", "Dan Gregor"],
      "production_company": "Universal Pictures",
      "actors": [
        "Robert Downey Jr.",
        "Antonio Banderas",
        "Michael Sheen",
        "Jim Broadbent",
        "Jessie Buckley",
        "Harry Collett",
        "Emma Thompson",
        "Rami Malek",
        "John Cena",
        "Kumail Nanjiani",
        "Octavia Spencer",
        "Tom Holland",
        "Craig Robinson",
        "Ralph Fiennes",
        "Selena Gomez"
      ],
      "description": "A physician who can talk to animals embarks on an adventure to find a legendary island with a young apprentice and a crew of strange pets.",
      "avg_vote": 5.6,
      "votes": 39245,
      "budget": 175000000,
      "usa_gross_income": 77047065,
      "worlwide_gross_income": 245891166,
      "metascore": 26,
      "reviews_from_users": 680,
      "reviews_from_critics": 180,
      "id": 51
    },
    {
      "imdb_title_id": "tt7134096",
      "title": "The Rhythm Section",
      "original_title": "The Rhythm Section",
      "year": 2020,
      "date_published": "2020-04-14",
      "genre": ["Action", "Drama", "Mystery"],
      "duration": 109,
      "country": ["UK", "USA", "Spain"],
      "language": ["English", "French"],
      "director": ["Reed Morano"],
      "writer": ["Mark Burnell", "Mark Burnell"],
      "production_company": "Paramount Pictures",
      "actors": [
        "Blake Lively",
        "Richard Brake",
        "Elly Curtis",
        "David Duggan",
        "Matilda Ziegler",
        "Bill O'Connell",
        "Raza Jaffrey",
        "Robert Mullins",
        "Ivana Basic",
        "Irma Mali",
        "Geoff Bell",
        "Tawfeek Barhom",
        "Jack McEvoy",
        "Peter Newington",
        "Jude Law"
      ],
      "description": "A woman seeks revenge against those who orchestrated a plane crash that killed her family.",
      "avg_vote": 5.2,
      "votes": 8816,
      "budget": 50000000,
      "usa_gross_income": 5437971,
      "worlwide_gross_income": 5989583,
      "metascore": 45,
      "reviews_from_users": 245,
      "reviews_from_critics": 117,
      "id": 56
    },
    {
      "imdb_title_id": "tt7504726",
      "title": "Il richiamo della foresta",
      "original_title": "The Call of the Wild",
      "year": 2020,
      "date_published": "2020-02-20",
      "genre": ["Adventure", "Drama", "Family"],
      "duration": 100,
      "country": ["Canada", "USA"],
      "language": ["English", "French"],
      "director": ["Chris Sanders"],
      "writer": ["Michael Green", "Jack London"],
      "production_company": "20th Century Studios",
      "actors": [
        "Harrison Ford",
        "Omar Sy",
        "Cara Gee",
        "Dan Stevens",
        "Bradley Whitford",
        "Jean Louisa Kelly",
        "Michael Horse",
        "Karen Gillan",
        "Colin Woodell",
        "Micah Fitzgerald",
        "Heather McPhaul",
        "Adam Fergus",
        "Stephanie Czajkowski",
        "Abraham Benrubi",
        "Thomas Adoue Polk"
      ],
      "description": "A sled dog struggles for survival in the wilds of the Yukon.",
      "avg_vote": 6.8,
      "votes": 29152,
      "budget": 135000000,
      "usa_gross_income": 62342368,
      "worlwide_gross_income": 107604626,
      "metascore": 47,
      "reviews_from_users": 427,
      "reviews_from_critics": 163,
      "id": 60
    },
    {
      "imdb_title_id": "tt7510346",
      "title": "The Turning - La casa del male",
      "original_title": "The Turning",
      "year": 2020,
      "date_published": "2020-08-11",
      "genre": ["Drama", "Horror", "Mystery"],
      "duration": 94,
      "country": ["UK", "Ireland", "Canada", "USA", "India"],
      "language": ["English"],
      "director": ["Floria Sigismondi"],
      "writer": ["Henry James", "Chad Hayes"],
      "production_company": "DreamWorks",
      "actors": [
        "Mackenzie Davis",
        "Finn Wolfhard",
        "Brooklynn Prince",
        "Barbara Marten",
        "Joely Richardson",
        "Niall Greig Fulton",
        "Denna Thomsen",
        "Kim Adis",
        "Darlene Garr"
      ],
      "description": "A young governess is hired by a man who has become responsible for his young nephew and niece after their parents' deaths. A modern take on Henry James' novella \"The Turn of the Screw.\"",
      "avg_vote": 3.8,
      "votes": 7549,
      "budget": 14000000,
      "usa_gross_income": 15472775,
      "worlwide_gross_income": 18596113,
      "metascore": 35,
      "reviews_from_users": 361,
      "reviews_from_critics": 103,
      "id": 62
    },
    {
      "imdb_title_id": "tt7713068",
      "title": "Birds of Prey e la fantasmagorica rinascita di Harley Quinn",
      "original_title": "Birds of Prey: And the Fantabulous Emancipation of One Harley Quinn",
      "year": 2020,
      "date_published": "2020-02-06",
      "genre": ["Action", "Adventure", "Crime"],
      "duration": 109,
      "country": ["USA"],
      "language": ["English", "Chinese"],
      "director": ["Cathy Yan"],
      "writer": ["Christina Hodson", "Paul Dini"],
      "production_company": "Clubhouse Pictures (II)",
      "actors": [
        "Margot Robbie",
        "Rosie Perez",
        "Mary Elizabeth Winstead",
        "Jurnee Smollett",
        "Ewan McGregor",
        "Ella Jay Basco",
        "Chris Messina",
        "Ali Wong",
        "David Ury",
        "Sara Montez",
        "Izabel Pakzad",
        "Daniel Bernhardt",
        "Kc Strubbe",
        "Jacky Shu",
        "Paloma Rabinov"
      ],
      "description": "After splitting with the Joker, Harley Quinn joins superheroes Black Canary, Huntress and Renee Montoya to save a young girl from an evil crime lord.",
      "avg_vote": 6.1,
      "votes": 137373,
      "budget": 84500000,
      "usa_gross_income": 84158461,
      "worlwide_gross_income": 201858461,
      "metascore": 60,
      "reviews_from_users": 2222,
      "reviews_from_critics": 372,
      "id": 64
    },
    {
      "imdb_title_id": "tt7798646",
      "title": "The Photograph",
      "original_title": "The Photograph",
      "year": 2020,
      "date_published": "2020-02-14",
      "genre": ["Drama", "Romance"],
      "duration": 106,
      "country": ["USA", "China"],
      "language": ["English"],
      "director": ["Stella Meghie"],
      "writer": ["Stella Meghie"],
      "production_company": "Perfect World Pictures",
      "actors": [
        "Issa Rae",
        "LaKeith Stanfield",
        "Chant茅 Adams",
        "Y'lan Noel",
        "Kelvin Harrison Jr.",
        "Lil Rel Howery",
        "Teyonah Parris",
        "Jasmine Cephas Jones",
        "Rylee Gabrielle King",
        "Phoenix Noelle",
        "Marsha Stephanie Blake",
        "Wakeema Hollis",
        "Maxwell Whittington-Cooper",
        "Rob Morgan",
        "Chelsea Peretti"
      ],
      "description": "A series of intertwining love stories set in the past and in the present.",
      "avg_vote": 5.9,
      "votes": 2646,
      "budget": 16000000,
      "usa_gross_income": 20578185,
      "worlwide_gross_income": 20690779,
      "metascore": 62,
      "reviews_from_users": 80,
      "reviews_from_critics": 63,
      "id": 66
    },
    {
      "imdb_title_id": "tt8244784",
      "title": "The Hunt",
      "original_title": "The Hunt",
      "year": 2020,
      "date_published": "2020-03-24",
      "genre": ["Action", "Horror", "Thriller"],
      "duration": 90,
      "country": ["USA"],
      "language": ["English"],
      "director": ["Craig Zobel"],
      "writer": ["Nick Cuse", "Damon Lindelof"],
      "production_company": "Blumhouse Productions",
      "actors": [
        "Betty Gilpin",
        "Hilary Swank",
        "Ike Barinholtz",
        "Wayne Duvall",
        "Ethan Suplee",
        "Emma Roberts",
        "Christopher Berry",
        "Sturgill Simpson",
        "Kate Nowlin",
        "Amy Madigan",
        "Reed Birney",
        "Glenn Howerton",
        "Steve Coulter",
        "Dean J. West",
        "Vince Pisani"
      ],
      "description": "Twelve strangers wake up in a clearing. They don't know where they are, or how they got there. They don't know they've been chosen - for a very specific purpose - The Hunt.",
      "avg_vote": 6.5,
      "votes": 52794,
      "budget": 14000000,
      "usa_gross_income": 5812500,
      "worlwide_gross_income": 10530977,
      "metascore": 50,
      "reviews_from_users": 757,
      "reviews_from_critics": 236,
      "id": 72
    },
    {
      "imdb_title_id": "tt8461224",
      "title": "The Tax Collector",
      "original_title": "The Tax Collector",
      "year": 2020,
      "date_published": "2020-08-07",
      "genre": ["Action", "Crime", "Drama"],
      "duration": 95,
      "country": ["USA"],
      "language": ["English"],
      "director": ["David Ayer"],
      "writer": ["David Ayer"],
      "production_company": "Cedar Park Entertainment",
      "actors": [
        "Bobby Soto",
        "Cinthya Carmona",
        "Shia LaBeouf",
        "Jose Conejo Martin",
        "Cheyenne Rae Hernandez",
        "Cle Sloan",
        "Richard Mesquita",
        "George Lopez",
        "Brian Martin Ortega",
        "Aaliyah Lopez",
        "Ricardo Gonzalez",
        "Elpidia Carrillo",
        "Lana Parrilla",
        "Gabriela Flores",
        "Noemi Gonzalez"
      ],
      "description": "A \"tax collector\" working for a local crime lord finds his family's safety compromised when the rival of his boss shows up in L.A. and upends the business.",
      "avg_vote": 4.7,
      "votes": 4862,
      "budget": 30000000,
      "usa_gross_income": 942666,
      "worlwide_gross_income": 942666,
      "metascore": 22,
      "reviews_from_users": 255,
      "reviews_from_critics": 47,
      "id": 73
    },
    {
      "imdb_title_id": "tt9086228",
      "title": "Gretel e Hansel",
      "original_title": "Gretel & Hansel",
      "year": 2020,
      "date_published": "2020-08-19",
      "genre": ["Fantasy", "Horror", "Mystery"],
      "duration": 87,
      "country": ["Canada", "USA", "Ireland", "South Africa"],
      "language": ["English"],
      "director": ["Oz Perkins"],
      "writer": ["Rob Hayes"],
      "production_company": "Orion Pictures",
      "actors": [
        "Sophia Lillis",
        "Samuel Leakey",
        "Alice Krige",
        "Jessica De Gouw",
        "Fiona O'Shaughnessy",
        "Donncha Crowley",
        "Jonathan Gunning",
        "Charles Babalola",
        "Giulia Doherty",
        "Jonathan Delaney Tynan",
        "Darlene Garr",
        "Melody Carrillo",
        "Nessa Last",
        "Harry O'Cualach谩in"
      ],
      "description": "A long time ago in a distant fairy tale countryside, a young girl leads her little brother into a dark wood in desperate search of food and work, only to stumble upon a nexus of terrifying evil.",
      "avg_vote": 5.3,
      "votes": 18390,
      "budget": 5000000,
      "usa_gross_income": 15347654,
      "worlwide_gross_income": 21966625,
      "metascore": 64,
      "reviews_from_users": 418,
      "reviews_from_critics": 154,
      "id": 77
    },
    {
      "imdb_title_id": "tt9173418",
      "title": "The Boy - La maledizione di Brahms",
      "original_title": "Brahms: The Boy II",
      "year": 2020,
      "date_published": "2020-03-19",
      "genre": ["Drama", "Horror", "Mystery"],
      "duration": 86,
      "country": ["USA", "China", "Canada", "Australia"],
      "language": ["English"],
      "director": ["William Brent Bell"],
      "writer": ["Stacey Menear", "Stacey Menear"],
      "production_company": "STX Films",
      "actors": [
        "Katie Holmes",
        "Christopher Convery",
        "Owain Yeoman",
        "Ralph Ineson",
        "Daphne Hoskins",
        "Keoni Rebeiro",
        "Joely Collins",
        "Oliver Rice",
        "Anjali Jay",
        "Natalie Moon",
        "Karl Mercer"
      ],
      "description": "After a family moves into the Heelshire Mansion, their young son soon makes friends with a life-like doll called Brahms.",
      "avg_vote": 4.6,
      "votes": 8755,
      "budget": 10000000,
      "usa_gross_income": 12611536,
      "worlwide_gross_income": 20311536,
      "metascore": 29,
      "reviews_from_users": 203,
      "reviews_from_critics": 107,
      "id": 78
    },
    {
      "imdb_title_id": "tt9208444",
      "title": "Impractical Jokers: The Movie",
      "original_title": "Impractical Jokers: The Movie",
      "year": 2020,
      "date_published": "2020-02-28",
      "genre": ["Comedy"],
      "duration": 92,
      "country": ["USA"],
      "language": ["English"],
      "director": ["Chris Henchy"],
      "writer": ["Chris Henchy", "Joe Gatto"],
      "production_company": "Funny or Die",
      "actors": [
        "Paula Abdul",
        "Joe Gatto",
        "James Murray",
        "Brian Quinn",
        "Sal Vulcano",
        "Jaden Smith",
        "Joey Fatone",
        "Salvatore Volcano Sr.",
        "Evan Castelloe",
        "Sierra Pond",
        "Madison Bailey",
        "Jessica Megan Rivera",
        "Sailor Larocque",
        "Andrea Andrade",
        "Camille Robinson"
      ],
      "description": "The story of a humiliating high school mishap from 1992 that sends the Impractical Jokers on the road competing in hidden-camera challenges for the chance to turn back the clock and redeem three of the four Jokers.",
      "avg_vote": 5.9,
      "votes": 4105,
      "budget": 3000000,
      "usa_gross_income": 10691091,
      "worlwide_gross_income": 10691091,
      "metascore": 39,
      "reviews_from_users": 152,
      "reviews_from_critics": 17,
      "id": 79
    },
    {
      "imdb_title_id": "tt9214832",
      "title": "Emma.",
      "original_title": "Emma.",
      "year": 2020,
      "date_published": "2020-03-27",
      "genre": ["Comedy", "Drama"],
      "duration": 124,
      "country": ["UK"],
      "language": ["English"],
      "director": ["Autumn de Wilde"],
      "writer": ["Eleanor Catton", "Jane Austen"],
      "production_company": "Working Title Films",
      "actors": [
        "Anya Taylor-Joy",
        "Angus Imrie",
        "Letty Thomas",
        "Gemma Whelan",
        "Bill Nighy",
        "Aidan White",
        "Edward Davis",
        "Chris White",
        "Rupert Graves",
        "Miranda Hart",
        "Myra McFadyen",
        "Esther Coles",
        "Suzy Bloom",
        "Suzanne Toase",
        "Nicholas Burns"
      ],
      "description": "In 1800s England, a well meaning but selfish young woman meddles in the love lives of her friends.",
      "avg_vote": 6.7,
      "votes": 19858,
      "budget": 10000000,
      "usa_gross_income": 10055355,
      "worlwide_gross_income": 25659965,
      "metascore": 71,
      "reviews_from_users": 314,
      "reviews_from_critics": 188,
      "id": 80
    },
    {
      "imdb_title_id": "tt9779516",
      "title": "Cosa mi lasci di te",
      "original_title": "I Still Believe",
      "year": 2020,
      "date_published": "2020-03-19",
      "genre": ["Biography", "Drama", "Music"],
      "duration": 116,
      "country": ["USA"],
      "language": ["English"],
      "director": ["Andrew Erwin", "Jon Erwin"],
      "writer": ["Jeremy Camp", "Jon Erwin"],
      "production_company": "Kevin Downes Productions",
      "actors": [
        "K.J. Apa",
        "Britt Robertson",
        "Nathan Parsons",
        "Gary Sinise",
        "Shania Twain",
        "Reuben Dodd",
        "Nicolas Bechtel",
        "Melissa Roxburgh",
        "Terry Serpico",
        "Tanya Christiansen",
        "Cameron Arnett",
        "Abigail Cowen",
        "Rushi Birudala",
        "Anjelah Johnson-Reyes",
        "Mike McGill"
      ],
      "description": "The true-life story of Christian music star Jeremy Camp and his journey of love and loss that looks to prove there is always hope.",
      "avg_vote": 6.5,
      "votes": 6196,
      "budget": 12000000,
      "usa_gross_income": 9868521,
      "worlwide_gross_income": 13681524,
      "metascore": 41,
      "reviews_from_users": 151,
      "reviews_from_critics": 52,
      "id": 84
    }
  ],
  "links": [
    { "common_genre": 1, "source": 1, "target": 2 },
    { "common_genre": 1, "source": 1, "target": 27 },
    { "common_genre": 1, "source": 1, "target": 28 },
    { "common_genre": 1, "source": 1, "target": 30 },
    { "common_genre": 1, "source": 1, "target": 35 },
    { "common_genre": 2, "source": 1, "target": 37 },
    { "common_genre": 1, "source": 1, "target": 40 },
    { "common_genre": 1, "source": 1, "target": 48 },
    { "common_genre": 1, "source": 1, "target": 51 },
    { "common_genre": 1, "source": 1, "target": 56 },
    { "common_genre": 1, "source": 1, "target": 60 },
    { "common_genre": 2, "source": 1, "target": 64 },
    { "common_genre": 1, "source": 1, "target": 72 },
    { "common_genre": 1, "source": 1, "target": 73 },
    { "common_genre": 1, "source": 1, "target": 77 },
    { "common_genre": 1, "source": 2, "target": 27 },
    { "common_genre": 1, "source": 2, "target": 28 },
    { "common_genre": 1, "source": 2, "target": 35 },
    { "common_genre": 1, "source": 2, "target": 37 },
    { "common_genre": 1, "source": 2, "target": 40 },
    { "common_genre": 1, "source": 2, "target": 48 },
    { "common_genre": 1, "source": 2, "target": 56 },
    { "common_genre": 1, "source": 2, "target": 64 },
    { "common_genre": 2, "source": 2, "target": 72 },
    { "common_genre": 1, "source": 2, "target": 73 },
    { "common_genre": 1, "source": 7, "target": 28 },
    { "common_genre": 2, "source": 7, "target": 36 },
    { "common_genre": 2, "source": 7, "target": 40 },
    { "common_genre": 2, "source": 7, "target": 48 },
    { "common_genre": 1, "source": 7, "target": 56 },
    { "common_genre": 2, "source": 7, "target": 62 },
    { "common_genre": 1, "source": 7, "target": 72 },
    { "common_genre": 2, "source": 7, "target": 77 },
    { "common_genre": 2, "source": 7, "target": 78 },
    { "common_genre": 1, "source": 27, "target": 28 },
    { "common_genre": 2, "source": 27, "target": 35 },
    { "common_genre": 2, "source": 27, "target": 37 },
    { "common_genre": 1, "source": 27, "target": 40 },
    { "common_genre": 1, "source": 27, "target": 48 },
    { "common_genre": 1, "source": 27, "target": 51 },
    { "common_genre": 1, "source": 27, "target": 56 },
    { "common_genre": 2, "source": 27, "target": 64 },
    { "common_genre": 1, "source": 27, "target": 72 },
    { "common_genre": 2, "source": 27, "target": 73 },
    { "common_genre": 1, "source": 27, "target": 79 },
    { "common_genre": 1, "source": 27, "target": 80 },
    { "common_genre": 1, "source": 28, "target": 30 },
    { "common_genre": 2, "source": 28, "target": 35 },
    { "common_genre": 1, "source": 28, "target": 37 },
    { "common_genre": 2, "source": 28, "target": 40 },
    { "common_genre": 1, "source": 28, "target": 43 },
    { "common_genre": 2, "source": 28, "target": 48 },
    { "common_genre": 2, "source": 28, "target": 56 },
    { "common_genre": 1, "source": 28, "target": 60 },
    { "common_genre": 1, "source": 28, "target": 62 },
    { "common_genre": 1, "source": 28, "target": 64 },
    { "common_genre": 1, "source": 28, "target": 66 },
    { "common_genre": 1, "source": 28, "target": 72 },
    { "common_genre": 2, "source": 28, "target": 73 },
    { "common_genre": 1, "source": 28, "target": 78 },
    { "common_genre": 1, "source": 28, "target": 80 },
    { "common_genre": 1, "source": 28, "target": 84 },
    { "common_genre": 1, "source": 30, "target": 35 },
    { "common_genre": 1, "source": 30, "target": 43 },
    { "common_genre": 1, "source": 30, "target": 56 },
    { "common_genre": 1, "source": 30, "target": 60 },
    { "common_genre": 1, "source": 30, "target": 62 },
    { "common_genre": 1, "source": 30, "target": 66 },
    { "common_genre": 1, "source": 30, "target": 73 },
    { "common_genre": 1, "source": 30, "target": 77 },
    { "common_genre": 1, "source": 30, "target": 78 },
    { "common_genre": 1, "source": 30, "target": 80 },
    { "common_genre": 1, "source": 30, "target": 84 },
    { "common_genre": 1, "source": 35, "target": 37 },
    { "common_genre": 1, "source": 35, "target": 40 },
    { "common_genre": 1, "source": 35, "target": 43 },
    { "common_genre": 1, "source": 35, "target": 48 },
    { "common_genre": 2, "source": 35, "target": 56 },
    { "common_genre": 1, "source": 35, "target": 60 },
    { "common_genre": 1, "source": 35, "target": 62 },
    { "common_genre": 2, "source": 35, "target": 64 },
    { "common_genre": 1, "source": 35, "target": 66 },
    { "common_genre": 1, "source": 35, "target": 72 },
    { "common_genre": 3, "source": 35, "target": 73 },
    { "common_genre": 1, "source": 35, "target": 78 },
    { "common_genre": 1, "source": 35, "target": 80 },
    { "common_genre": 1, "source": 35, "target": 84 },
    { "common_genre": 1, "source": 36, "target": 40 },
    { "common_genre": 1, "source": 36, "target": 48 },
    { "common_genre": 1, "source": 36, "target": 56 },
    { "common_genre": 2, "source": 36, "target": 62 },
    { "common_genre": 1, "source": 36, "target": 72 },
    { "common_genre": 2, "source": 36, "target": 77 },
    { "common_genre": 2, "source": 36, "target": 78 },
    { "common_genre": 1, "source": 37, "target": 40 },
    { "common_genre": 1, "source": 37, "target": 48 },
    { "common_genre": 2, "source": 37, "target": 51 },
    { "common_genre": 1, "source": 37, "target": 56 },
    { "common_genre": 1, "source": 37, "target": 60 },
    { "common_genre": 2, "source": 37, "target": 64 },
    { "common_genre": 1, "source": 37, "target": 72 },
    { "common_genre": 1, "source": 37, "target": 73 },
    { "common_genre": 1, "source": 37, "target": 79 },
    { "common_genre": 1, "source": 37, "target": 80 },
    { "common_genre": 3, "source": 40, "target": 48 },
    { "common_genre": 1, "source": 40, "target": 56 },
    { "common_genre": 1, "source": 40, "target": 62 },
    { "common_genre": 1, "source": 40, "target": 64 },
    { "common_genre": 2, "source": 40, "target": 72 },
    { "common_genre": 1, "source": 40, "target": 73 },
    { "common_genre": 1, "source": 40, "target": 77 },
    { "common_genre": 1, "source": 40, "target": 78 },
    { "common_genre": 1, "source": 43, "target": 56 },
    { "common_genre": 1, "source": 43, "target": 60 },
    { "common_genre": 1, "source": 43, "target": 62 },
    { "common_genre": 1, "source": 43, "target": 66 },
    { "common_genre": 1, "source": 43, "target": 73 },
    { "common_genre": 1, "source": 43, "target": 78 },
    { "common_genre": 1, "source": 43, "target": 80 },
    { "common_genre": 2, "source": 43, "target": 84 },
    { "common_genre": 1, "source": 48, "target": 56 },
    { "common_genre": 1, "source": 48, "target": 62 },
    { "common_genre": 1, "source": 48, "target": 64 },
    { "common_genre": 2, "source": 48, "target": 72 },
    { "common_genre": 1, "source": 48, "target": 73 },
    { "common_genre": 1, "source": 48, "target": 77 },
    { "common_genre": 1, "source": 48, "target": 78 },
    { "common_genre": 2, "source": 51, "target": 60 },
    { "common_genre": 1, "source": 51, "target": 64 },
    { "common_genre": 1, "source": 51, "target": 79 },
    { "common_genre": 1, "source": 51, "target": 80 },
    { "common_genre": 1, "source": 56, "target": 60 },
    { "common_genre": 2, "source": 56, "target": 62 },
    { "common_genre": 1, "source": 56, "target": 64 },
    { "common_genre": 1, "source": 56, "target": 66 },
    { "common_genre": 1, "source": 56, "target": 72 },
    { "common_genre": 2, "source": 56, "target": 73 },
    { "common_genre": 1, "source": 56, "target": 77 },
    { "common_genre": 2, "source": 56, "target": 78 },
    { "common_genre": 1, "source": 56, "target": 80 },
    { "common_genre": 1, "source": 56, "target": 84 },
    { "common_genre": 1, "source": 60, "target": 62 },
    { "common_genre": 1, "source": 60, "target": 64 },
    { "common_genre": 1, "source": 60, "target": 66 },
    { "common_genre": 1, "source": 60, "target": 73 },
    { "common_genre": 1, "source": 60, "target": 78 },
    { "common_genre": 1, "source": 60, "target": 80 },
    { "common_genre": 1, "source": 60, "target": 84 },
    { "common_genre": 1, "source": 62, "target": 66 },
    { "common_genre": 1, "source": 62, "target": 72 },
    { "common_genre": 1, "source": 62, "target": 73 },
    { "common_genre": 2, "source": 62, "target": 77 },
    { "common_genre": 3, "source": 62, "target": 78 },
    { "common_genre": 1, "source": 62, "target": 80 },
    { "common_genre": 1, "source": 62, "target": 84 },
    { "common_genre": 1, "source": 64, "target": 72 },
    { "common_genre": 2, "source": 64, "target": 73 },
    { "common_genre": 1, "source": 66, "target": 73 },
    { "common_genre": 1, "source": 66, "target": 78 },
    { "common_genre": 1, "source": 66, "target": 80 },
    { "common_genre": 1, "source": 66, "target": 84 },
    { "common_genre": 1, "source": 72, "target": 73 },
    { "common_genre": 1, "source": 72, "target": 77 },
    { "common_genre": 1, "source": 72, "target": 78 },
    { "common_genre": 1, "source": 73, "target": 78 },
    { "common_genre": 1, "source": 73, "target": 80 },
    { "common_genre": 1, "source": 73, "target": 84 },
    { "common_genre": 2, "source": 77, "target": 78 },
    { "common_genre": 1, "source": 78, "target": 80 },
    { "common_genre": 1, "source": 78, "target": 84 },
    { "common_genre": 1, "source": 79, "target": 80 },
    { "common_genre": 1, "source": 80, "target": 84 }
  ]
}
